{ "nodes": [ {"id": ".net", "name": ".net", "value": 10, "actualValue": 1, "group": 0},{"id": "c#", "name": "c#", "value": 20, "actualValue": 8, "group": 3},{"id": "javascript", "name": "javascript", "value": 14.2857142857143, "actualValue": 4, "group": 1},{"id": "jquery", "name": "jquery", "value": 14.2857142857143, "actualValue": 4, "group": 1},{"id": "iphone", "name": "iphone", "value": 17.1428571428571, "actualValue": 6, "group": 0},{"id": "objective-c", "name": "objective-c", "value": 14.2857142857143, "actualValue": 4, "group": 0},{"id": "css", "name": "css", "value": 11.4285714285714, "actualValue": 2, "group": 1},{"id": "html", "name": "html", "value": 12.8571428571429, "actualValue": 3, "group": 1},{"id": "c", "name": "c", "value": 10, "actualValue": 1, "group": 3},{"id": "c++", "name": "c++", "value": 14.2857142857143, "actualValue": 4, "group": 3},{"id": "ruby", "name": "ruby", "value": 10, "actualValue": 1, "group": 0},{"id": "ruby-on-rails", "name": "ruby-on-rails", "value": 11.4285714285714, "actualValue": 2, "group": 3},{"id": "android", "name": "android", "value": 10, "actualValue": 1, "group": 0},{"id": "java", "name": "java", "value": 20, "actualValue": 8, "group": 3},{"id": "ios", "name": "ios", "value": 11.4285714285714, "actualValue": 2, "group": 0},{"id": "django", "name": "django", "value": 10, "actualValue": 1, "group": 0},{"id": "python", "name": "python", "value": 11.4285714285714, "actualValue": 2, "group": 3},{"id": "asp.net", "name": "asp.net", "value": 11.4285714285714, "actualValue": 2, "group": 0},{"id": "cocoa-touch", "name": "cocoa-touch", "value": 11.4285714285714, "actualValue": 2, "group": 0},{"id": "sql", "name": "sql", "value": 12.8571428571429, "actualValue": 3, "group": 0},{"id": "sql-server", "name": "sql-server", "value": 11.4285714285714, "actualValue": 2, "group": 2},{"id": "winforms", "name": "winforms", "value": 10, "actualValue": 1, "group": 0},{"id": "mysql", "name": "mysql", "value": 11.4285714285714, "actualValue": 2, "group": 2},{"id": "eclipse", "name": "eclipse", "value": 10, "actualValue": 1, "group": 0},{"id": "spring", "name": "spring", "value": 10, "actualValue": 1, "group": 0},{"id": "linq", "name": "linq", "value": 10, "actualValue": 1, "group": 0},{"id": "hibernate", "name": "hibernate", "value": 10, "actualValue": 1, "group": 0},{"id": "wpf", "name": "wpf", "value": 10, "actualValue": 1, "group": 0},{"id": "ruby-on-rails-3", "name": "ruby-on-rails-3", "value": 10, "actualValue": 1, "group": 0},{"id": "php", "name": "php", "value": 11.4285714285714, "actualValue": 2, "group": 1},{"id": "ipad", "name": "ipad", "value": 10, "actualValue": 1, "group": 0},{"id": "visual-studio", "name": "visual-studio", "value": 11.4285714285714, "actualValue": 2, "group": 0},{"id": "visual-studio-2010", "name": "visual-studio-2010", "value": 10, "actualValue": 1, "group": 0},{"id": "tsql", "name": "tsql", "value": 11.4285714285714, "actualValue": 2, "group": 0},{"id": "string", "name": "string", "value": 10, "actualValue": 1, "group": 0},{"id": "ajax", "name": "ajax", "value": 11.4285714285714, "actualValue": 2, "group": 0},{"id": "xcode", "name": "xcode", "value": 10, "actualValue": 1, "group": 0},{"id": "stl", "name": "stl", "value": 10, "actualValue": 1, "group": 0},{"id": "asp.net-mvc", "name": "asp.net-mvc", "value": 11.4285714285714, "actualValue": 2, "group": 0},{"id": "multithreading", "name": "multithreading", "value": 11.4285714285714, "actualValue": 2, "group": 0},{"id": "cocoa", "name": "cocoa", "value": 10, "actualValue": 1, "group": 0},{"id": "jquery-ui", "name": "jquery-ui", "value": 10, "actualValue": 1, "group": 0},{"id": "c++11", "name": "c++11", "value": 10, "actualValue": 1, "group": 0},{"id": "arrays", "name": "arrays", "value": 10, "actualValue": 1, "group": 0},{"id": "jpa", "name": "jpa", "value": 10, "actualValue": 1, "group": 0},{"id": "list", "name": "list", "value": 10, "actualValue": 1, "group": 0},{"id": "uitableview", "name": "uitableview", "value": 10, "actualValue": 1, "group": 0},{"id": "swing", "name": "swing", "value": 10, "actualValue": 1, "group": 0},{"id": "bash", "name": "bash", "value": 10, "actualValue": 1, "group": 0},{"id": "shell", "name": "shell", "value": 10, "actualValue": 1, "group": 0},{"id": "boost", "name": "boost", "value": 10, "actualValue": 1, "group": 0} ], "edges": [ {"source": 0, "target": 1, "actualValue": 1403, "value": 7},{"source": 2, "target": 3, "actualValue": 925, "value": 5.1386292834891},{"source": 4, "target": 5, "actualValue": 627, "value": 3.97819314641745},{"source": 6, "target": 7, "actualValue": 488, "value": 3.43691588785047},{"source": 8, "target": 9, "actualValue": 453, "value": 3.3006230529595},{"source": 10, "target": 11, "actualValue": 385, "value": 3.03582554517134},{"source": 7, "target": 2, "actualValue": 357, "value": 2.92679127725857},{"source": 12, "target": 13, "actualValue": 350, "value": 2.89953271028037},{"source": 14, "target": 4, "actualValue": 330, "value": 2.82165109034268},{"source": 15, "target": 16, "actualValue": 327, "value": 2.80996884735203},{"source": 17, "target": 1, "actualValue": 314, "value": 2.75934579439252},{"source": 18, "target": 4, "actualValue": 270, "value": 2.5880062305296},{"source": 19, "target": 20, "actualValue": 263, "value": 2.5607476635514},{"source": 1, "target": 21, "actualValue": 230, "value": 2.43224299065421},{"source": 22, "target": 19, "actualValue": 229, "value": 2.42834890965732},{"source": 23, "target": 13, "actualValue": 229, "value": 2.42834890965732},{"source": 13, "target": 24, "actualValue": 223, "value": 2.40498442367601},{"source": 1, "target": 25, "actualValue": 210, "value": 2.35436137071651},{"source": 26, "target": 13, "actualValue": 210, "value": 2.35436137071651},{"source": 7, "target": 3, "actualValue": 203, "value": 2.32710280373832},{"source": 1, "target": 27, "actualValue": 201, "value": 2.31931464174455},{"source": 11, "target": 28, "actualValue": 198, "value": 2.30763239875389},{"source": 22, "target": 29, "actualValue": 197, "value": 2.30373831775701},{"source": 14, "target": 5, "actualValue": 196, "value": 2.29984423676012},{"source": 30, "target": 4, "actualValue": 188, "value": 2.26869158878505},{"source": 18, "target": 5, "actualValue": 186, "value": 2.26090342679128},{"source": 6, "target": 2, "actualValue": 173, "value": 2.21028037383178},{"source": 31, "target": 32, "actualValue": 166, "value": 2.18302180685358},{"source": 20, "target": 33, "actualValue": 165, "value": 2.1791277258567},{"source": 13, "target": 34, "actualValue": 164, "value": 2.17523364485981},{"source": 35, "target": 3, "actualValue": 164, "value": 2.17523364485981},{"source": 4, "target": 36, "actualValue": 164, "value": 2.17523364485981},{"source": 9, "target": 37, "actualValue": 158, "value": 2.1518691588785},{"source": 38, "target": 1, "actualValue": 158, "value": 2.1518691588785},{"source": 13, "target": 39, "actualValue": 146, "value": 2.10514018691589},{"source": 1, "target": 31, "actualValue": 145, "value": 2.101246105919},{"source": 40, "target": 5, "actualValue": 143, "value": 2.09345794392523},{"source": 3, "target": 41, "actualValue": 141, "value": 2.08566978193146},{"source": 9, "target": 42, "actualValue": 140, "value": 2.08177570093458},{"source": 43, "target": 29, "actualValue": 140, "value": 2.08177570093458},{"source": 13, "target": 44, "actualValue": 140, "value": 2.08177570093458},{"source": 19, "target": 33, "actualValue": 135, "value": 2.06230529595016},{"source": 45, "target": 16, "actualValue": 135, "value": 2.06230529595016},{"source": 4, "target": 46, "actualValue": 133, "value": 2.05451713395639},{"source": 35, "target": 2, "actualValue": 130, "value": 2.04283489096573},{"source": 1, "target": 39, "actualValue": 128, "value": 2.03504672897196},{"source": 13, "target": 47, "actualValue": 125, "value": 2.02336448598131},{"source": 48, "target": 49, "actualValue": 122, "value": 2.01168224299065},{"source": 17, "target": 38, "actualValue": 122, "value": 2.01168224299065},{"source": 50, "target": 9, "actualValue": 119, "value": 2} ]}